xia_compiler_openapi/__init__.py
xia_compiler_openapi/compiler.cp311-win_amd64.pyd
xia_compiler_openapi-0.1.23.dist-info/LICENSE.txt
xia_compiler_openapi-0.1.23.dist-info/METADATA
xia_compiler_openapi-0.1.23.dist-info/WHEEL
xia_compiler_openapi-0.1.23.dist-info/top_level.txt
xia_compiler_openapi-0.1.23.dist-info/RECORD
