Metadata-Version: 2.1
Name: xia-compiler-openapi
Version: 0.1.23
Home-page: https://develop.x-i-a.com/docs/xia-compiler-openapi/0.1.23/index.html
Author: X-I-A
Author-email: admin@x-i-a.com
Requires-Python: >=3.9
License-File: LICENSE.txt
Requires-Dist: xia-api
